automation/__init__.py
automation/cli.py
automation/config.py
automation/logging.py
automation/parse_inputs.py
automation/validation.py
automation/base/__init__.py
automation/base/base_function.py
automation/base/git_actions.py
mauto-0.0.1.dev14.dist-info/METADATA
mauto-0.0.1.dev14.dist-info/WHEEL
mauto-0.0.1.dev14.dist-info/entry_points.txt
mauto-0.0.1.dev14.dist-info/top_level.txt
mauto-0.0.1.dev14.dist-info/RECORD
