Metadata-Version: 2.1
Name: mauto
Version: 0.0.1.dev14
Summary: Automate deployment of monitoring tools
Home-page: https://github.com/tomarv2/mauto
Author: Varun Tomar
Author-email: varuntomar2019@gmail.com
License: UNKNOWN
Platform: UNKNOWN
Classifier: Programming Language :: Python :: 3.6
Classifier: Operating System :: OS Independent
Requires-Python: >=3.6
Requires-Dist: certifi (==2020.4.5.1)
Requires-Dist: chardet (==3.0.4)
Requires-Dist: gitdb2 (==4.0.2)
Requires-Dist: GitPython (==3.1.1)
Requires-Dist: idna (==2.9)
Requires-Dist: in-place (==0.4.0)
Requires-Dist: PyYAML (==5.3.1)
Requires-Dist: requests (==2.23.0)
Requires-Dist: six (==1.14.0)
Requires-Dist: smmap2 (==3.0.1)
Requires-Dist: urllib3 (==1.25.9)
Requires-Dist: yamllint (==1.23.0)
Requires-Dist: PyStaticConfiguration (==0.10.4)
Requires-Dist: mock (==4.0.2)
Requires-Dist: pytest (==5.4.1)
Requires-Dist: sonarqube-api (==1.3.1)
Requires-Dist: docker (==4.2.0)
Requires-Dist: kazoo (==2.5.0)
Requires-Dist: pykafka
Requires-Dist: validate-email (==1.3)
Requires-Dist: ruamel.yaml (==0.16.10)
Requires-Dist: starlette (==0.13.4)
Requires-Dist: Jinja2 (==2.11.2)
Requires-Dist: click (==7.1.2)
Requires-Dist: tabulate (==0.8.7)
